{
  "action_id": "gov_action1u9x73kwufaxa70lfy59g4ynwyrcsaxdcd0gxzzmh67s9fxq4j8hqqk2phgh",
  "title": "gov_action1u9x73kwufaxa70lfy59g4ynwyrcsaxdcd0gxzzmh67s9fxq4j8hqqk2phgh",
  "type": "InfoAction",
  "status": "expired",
  "source": {
    "origin": "governance fetch pipeline",
    "raw_input_hash": "sha256:d6436b02b3f8cf5e01b88bdf74760244ae8827c83d24d6fa3765b86a6b903f33",
    "detected_at": "2026-02-09T18:50:25.950966+00:00"
  },
  "decision": {
    "vote": "YES",
    "published_at": "2026-03-25T13:00:02.009603+00:00",
    "signed": false,
    "transaction_hash": null
  },
  "rationale": {
    "summary": "Network DRep distribution used as one signal, not authority.",
    "markdown_path": "/data/output/gov_action1u9x73kwufaxa70lfy59g4ynwyrcsaxdcd0gxzzmh67s9fxq4j8hqqk2phgh-d6436b02b3f8/rationale.md",
    "missing_evidence": []
  },
  "reproducibility": {
    "soul_repo": "beacn-drep-soul",
    "soul_commit": "f9f8fbe5a6ecfe866593cbd98f9ac10c63cd4c45",
    "resources_repo": "beacn-drep-resources",
    "resources_commit": "19015beec8cfe8ac067751400a960c9d5af3383f",
    "core_commit": "128c9d269d33c2156e672c330f28403637e8a4ce",
    "resource_ids_used": [
      "gov_actions_api",
      "gov_actions_snapshot",
      "drep_vote_history_snapshot",
      "gov_actions_all_snapshot",
      "gov_actions_active_snapshot",
      "gov_action_flags_snapshot",
      "gov_poll_runs_snapshot",
      "top_drep_votes_snapshot"
    ]
  },
  "inputs_used": [
    {
      "resource_id": "gov_actions_api",
      "type": "csv",
      "path": "registries/resource_registry.csv"
    },
    {
      "resource_id": "gov_actions_snapshot",
      "type": "csv",
      "path": "registries/resource_registry.csv"
    },
    {
      "resource_id": "drep_vote_history_snapshot",
      "type": "csv",
      "path": "registries/resource_registry.csv"
    },
    {
      "resource_id": "gov_actions_all_snapshot",
      "type": "csv",
      "path": "registries/resource_registry.csv"
    },
    {
      "resource_id": "gov_actions_active_snapshot",
      "type": "csv",
      "path": "registries/resource_registry.csv"
    },
    {
      "resource_id": "gov_action_flags_snapshot",
      "type": "csv",
      "path": "registries/resource_registry.csv"
    },
    {
      "resource_id": "gov_poll_runs_snapshot",
      "type": "csv",
      "path": "registries/resource_registry.csv"
    },
    {
      "resource_id": "top_drep_votes_snapshot",
      "type": "csv",
      "path": "registries/resource_registry.csv"
    }
  ],
  "scoring": {
    "budget_pressure": 0.0,
    "conflict_risk": 0.0,
    "technical_value": 0.45,
    "governance_alignment": 1.0
  },
  "freshness": {
    "snapshot_age_seconds": 82,
    "max_allowed_seconds": 21600,
    "is_stale": false,
    "snapshot_time": "2026-03-25T13:31:10.615500+00:00"
  }
}
