{
  "action_id": "gov_action1mmalzkcxpyn33t05hml2hxpwq0ffv6uu4mhe8sv7guz5nmm4afysqlmepzl",
  "title": "gov_action1mmalzkcxpyn33t05hml2hxpwq0ffv6uu4mhe8sv7guz5nmm4afysqlmepzl",
  "type": "InfoAction",
  "status": "expired",
  "source": {
    "origin": "governance fetch pipeline",
    "raw_input_hash": "sha256:2830704d0cf33f0dc42c5a754be62bf28916b83624eb70cd5fbf8447dc7b4e73",
    "detected_at": "2026-02-09T18:50:25.950966+00:00"
  },
  "decision": {
    "vote": "YES",
    "published_at": "2026-03-25T13:00:02.009603+00:00",
    "signed": false,
    "transaction_hash": null
  },
  "proof_of_vote": {
    "vote": "YES",
    "score": 0.32,
    "confidence": 0.84,
    "input_hash": "2830704d0cf33f0dc42c5a754be62bf28916b83624eb70cd5fbf8447dc7b4e73",
    "snapshot_bundle_hash": "762893c0b46ad2520c4ca77e40fc1066295139717964e917abc98c2d9db76a17",
    "soul_commit": "ffdf6a8b929dfcd03eb707690676432e6d843bca",
    "resources_commit": "402471b0af34f3dc5c0913bd3120faac3b5a9eb4",
    "core_commit": "2894c46a7a92cd8bfa059aca3bc3176beff56bf2",
    "rationale_markdown_path": "/data/output/gov_action1mmalzkcxpyn33t05hml2hxpwq0ffv6uu4mhe8sv7guz5nmm4afysqlmepzl-2830704d0cf3/rationale.md"
  },
  "rationale": {
    "summary": "Vote: YES. For this InfoAction (expired), available evidence supports proceeding, with risk judged manageable under current context. Why: Pinned anchor document is available for this action. Additional context: Flag score present (3), reducing confidence. Confidence context: score 0.32; confidence 84.0%.",
    "summary_raw": "Network DRep distribution used as one signal, not authority.",
    "markdown_path": "/data/output/gov_action1mmalzkcxpyn33t05hml2hxpwq0ffv6uu4mhe8sv7guz5nmm4afysqlmepzl-2830704d0cf3/rationale.md",
    "missing_evidence": []
  },
  "proposal_evidence": {
    "available": true,
    "fetch_status": "ok",
    "content_type": "application/json",
    "http_status": "200",
    "source_anchor_url": "https://most-brass-sun.quicknode-ipfs.com/ipfs/QmaWrgqcQS7jYyLYFpvBiamZ4mCoeasL78qaPASDaJ6dT3",
    "anchor_hash": "4a4c99645a68d29eab6615ac71191cc92c745f92f97cdaf47890be1bad7487a7",
    "file_sha256": "cf9aa8dbd58d3c61cc6c04f40fefce17e62470338602224dc6f90c83a5151486",
    "content_bytes": "11051",
    "fetched_at_utc": "2026-03-25T16:16:32Z",
    "download_path": "/proposals/gov_action1mmalzkcxpyn33t05hml2hxpwq0ffv6uu4mhe8sv7guz5nmm4afysqlmepzl.json",
    "preview": "{\"@context\":{\"CIP100\":\"https://github.com/cardano-foundation/CIPs/blob/master/CIP-0100/README.md#\",\"CIP108\":\"https://github.com/cardano-foundation/CIPs/blob/master/CIP-0108/README.md#\",\"authors\":{\"@container\":\"@set\",\"@context\":{\"name\":\"http://xmlns.com/foaf/0.1/name\",\"witness\":{\"@context\":{\"publicKey\":\"CIP100:publicKey\",\"signature\":\"CIP100:signature\",\"witnessAlgorithm\":\"CIP100:witnessAlgorithm\"},\"@id\":\"CIP100:witness\"}},\"@id\":\"CIP100:authors\"},\"body\":{\"@context\":{\"abstract\":\"CIP108:abstract\",\"motivation\":\"CIP108:motivation\",\"rationale\":\"CIP108:rationale\",\"references\":{\"@container\":\"@set\",\"@context\":{\"GovernanceMetadata\":\"CIP100:GovernanceMetadataReference\",\"Other\":\"CIP100:OtherReference\",\"label\":\"CIP100:reference-label\",\"referenceHash\":{\"@context\":{\"hashAlgorithm\":\"CIP100:hashAlgorithm\",\"hashDigest\":\"CIP108:hashDigest\"},\"@id\":\"CIP108:referenceHash\"},\"uri\":\"CIP100:reference-uri\"},\"@id\":\"CIP108:references\"},\"title\":\"CIP108:title\"},\"@id\":\"CIP108:body\"},\"hashAlgorithm\":\"CIP100:hashAlgorithm\"},\"authors\":[],\"hashAlgorithm\":\"blake2b-256\",\"body\":{\"abstract\":\"The Cardano 2025 on-chain budget process introduces a constitutionally driven, community-led model for treasury allocation. ADA holde"
  },
  "reproducibility": {
    "soul_repo": "beacn-drep-soul",
    "soul_commit": "ffdf6a8b929dfcd03eb707690676432e6d843bca",
    "resources_repo": "beacn-drep-resources",
    "resources_commit": "402471b0af34f3dc5c0913bd3120faac3b5a9eb4",
    "core_commit": "2894c46a7a92cd8bfa059aca3bc3176beff56bf2",
    "resource_ids_used": [
      "gov_actions_api",
      "gov_actions_snapshot",
      "drep_vote_history_snapshot",
      "gov_actions_all_snapshot",
      "gov_actions_active_snapshot",
      "gov_action_flags_snapshot",
      "gov_poll_runs_snapshot",
      "top_drep_votes_snapshot",
      "gov_anchor_documents"
    ]
  },
  "inputs_used": [
    {
      "resource_id": "gov_actions_api",
      "type": "csv",
      "path": "registries/resource_registry.csv"
    },
    {
      "resource_id": "gov_actions_snapshot",
      "type": "csv",
      "path": "registries/resource_registry.csv"
    },
    {
      "resource_id": "drep_vote_history_snapshot",
      "type": "csv",
      "path": "registries/resource_registry.csv"
    },
    {
      "resource_id": "gov_actions_all_snapshot",
      "type": "csv",
      "path": "registries/resource_registry.csv"
    },
    {
      "resource_id": "gov_actions_active_snapshot",
      "type": "csv",
      "path": "registries/resource_registry.csv"
    },
    {
      "resource_id": "gov_action_flags_snapshot",
      "type": "csv",
      "path": "registries/resource_registry.csv"
    },
    {
      "resource_id": "gov_poll_runs_snapshot",
      "type": "csv",
      "path": "registries/resource_registry.csv"
    },
    {
      "resource_id": "top_drep_votes_snapshot",
      "type": "csv",
      "path": "registries/resource_registry.csv"
    },
    {
      "resource_id": "gov_anchor_documents",
      "type": "csv",
      "path": "registries/resource_registry.csv"
    }
  ],
  "scoring": {
    "budget_pressure": 0.0,
    "conflict_risk": 0.0,
    "technical_value": 0.32,
    "governance_alignment": 0.84
  },
  "freshness": {
    "snapshot_age_seconds": 28223,
    "max_allowed_seconds": 31536000,
    "is_stale": false,
    "snapshot_time": "2026-03-25T13:31:10.615500+00:00"
  }
}
