{
  "generated_at": "2026-07-22T11:34:05Z",
  "current_versions": {
    "soul_commit": "c813ed97f64dba61150d01964327553baf720d38",
    "resources_commit": "9e6d7de921490a42032dbcf21a53abc34f881376",
    "core_commit": "a055839739ee45148170efd5bb67ffe6e52ab25d"
  },
  "pipeline": {
    "last_scan_at": "2026-07-22T11:34:05Z",
    "last_decision_at": "2026-07-22T11:34:05Z",
    "last_publish_at": "2026-07-22T11:34:05Z",
    "anchor_fetch": {
      "total": 150,
      "ok": 148,
      "ok_cached": 146,
      "failed": 2,
      "coverage_pct": 98.67,
      "failure_buckets": {
        "http_error:404": 2
      }
    }
  },
  "integrity": {
    "hidden_inputs_allowed": false,
    "undeclared_resources_allowed": false,
    "manual_override_enabled": false,
    "private_assistant_context_allowed": false,
    "private_memory_allowed": false,
    "policy_doc": "docs/PUBLIC_CONTEXT_AND_LIMITS.md"
  }
}
