{
  "generated_at": "2026-07-10T03:37:25Z",
  "soul": {
    "repo": "beacn-drep-soul",
    "commit": "204e26c8230587b4b4df20eeb0a8485d478b54a9",
    "path": "README.md"
  },
  "resources": {
    "repo": "beacn-drep-resources",
    "commit": "ef21df7fcecbb56f66c12028d9c7dafb58b68c52",
    "registry_path": "registries/resource_registry.csv"
  },
  "core": {
    "repo": "beacn-drep-core",
    "version": "0.2.0",
    "commit": "477180351445c61a6d12f92a427347abee714f40"
  },
  "stats": {
    "actions_seen": 298,
    "decisions_published": 298,
    "votes_cast": 0,
    "abstentions": 192,
    "needs_more_info": 99,
    "anchor_fetch_total": 298,
    "anchor_fetch_ok": 294,
    "anchor_fetch_failed": 4,
    "anchor_fetch_coverage_pct": 98.66
  },
  "latest_actions": [
    {
      "action_id": "529dccaadaa000746c22f1682574cb3f436eeba4d19710b90791a54226dc96d7#0",
      "title": "Withdraw 120,000,000 ada for AlphaGrowth\u2019s Cardano PRIME",
      "type": "TreasuryWithdrawals",
      "decision": "ABSTAIN",
      "published_at": "2026-07-10T03:21:53.574905+00:00"
    },
    {
      "action_id": "2f429bde312c0806bd16199da10f4145da9807161e99d4486174c6fb9a91f983#0",
      "title": "Revised Cardano dOSPO and OMF Program Proposal",
      "type": "TreasuryWithdrawals",
      "decision": "ABSTAIN",
      "published_at": "2026-07-10T03:21:53.574905+00:00"
    },
    {
      "action_id": "b518efa466593906ab388f978b3695449809aacdf28d2aaf4eb5ba16b3c24a1e#0",
      "title": "Approve Cardano Foundation as New Managing Entity of Project Catalyst",
      "type": "InfoAction",
      "decision": "ABSTAIN",
      "published_at": "2026-07-10T03:21:53.574905+00:00"
    },
    {
      "action_id": "8ad3d454f3496a35cb0d07b0fd32f687f66338b7d60e787fc0a22939e5d8833e#8",
      "title": "Withdraw \u20b3220,914 for Dolos: Sustaining a Lightweight Cardano Data Node",
      "type": "TreasuryWithdrawals",
      "decision": "ABSTAIN",
      "published_at": "2026-07-10T03:21:53.574905+00:00"
    },
    {
      "action_id": "8ad3d454f3496a35cb0d07b0fd32f687f66338b7d60e787fc0a22939e5d8833e#33",
      "title": "Withdraw \u20b3199,911 for OpShin - Python Smart Contracts for Cardano",
      "type": "TreasuryWithdrawals",
      "decision": "ABSTAIN",
      "published_at": "2026-07-10T03:21:53.574905+00:00"
    },
    {
      "action_id": "73e171a4c0730b4b59ecae271ab89f12a9d56360b02920e1f95107dbdc1d6762#2",
      "title": "IO: Consensus Initiative",
      "type": "TreasuryWithdrawals",
      "decision": "ABSTAIN",
      "published_at": "2026-07-10T03:21:53.574905+00:00"
    },
    {
      "action_id": "03f671791fd97011f30e4d6b76c9a91f4f6bcfb60ee37e5399b9545bb3f2757a#0",
      "title": "Loan \u20b35,000,000 to Expand Cardano's Global Listings",
      "type": "TreasuryWithdrawals",
      "decision": "ABSTAIN",
      "published_at": "2026-07-10T03:21:53.574905+00:00"
    },
    {
      "action_id": "8ad3d454f3496a35cb0d07b0fd32f687f66338b7d60e787fc0a22939e5d8833e#30",
      "title": "Withdraw \u20b33,000,000 for High-yield RWA Asset for Cardano: Tokenized Real Estate",
      "type": "TreasuryWithdrawals",
      "decision": "ABSTAIN",
      "published_at": "2026-07-10T03:21:53.574905+00:00"
    },
    {
      "action_id": "af15a6627176f13be28100d7aa96a40f103f63c98e553869e38ab135ff4292cd#0",
      "title": "Tweag Core Cardano Infrastructure: Treasury Withdrawal 2026\u20132028",
      "type": "TreasuryWithdrawals",
      "decision": "ABSTAIN",
      "published_at": "2026-07-10T03:21:53.574905+00:00"
    },
    {
      "action_id": "8ad3d454f3496a35cb0d07b0fd32f687f66338b7d60e787fc0a22939e5d8833e#16",
      "title": "Withdraw \u20b3583,000 for Eternl Maintenance administered by Intersect",
      "type": "TreasuryWithdrawals",
      "decision": "ABSTAIN",
      "published_at": "2026-07-10T03:21:53.574905+00:00"
    },
    {
      "action_id": "a633504ddc47a852c4ae033c750597d011a3daf00a0f6bbd48de4c52ef1022dc#0",
      "title": "DeltaDeFi: Hydra Trading Infrastructure Budget (\u20b31,500,000)",
      "type": "InfoAction",
      "decision": "ABSTAIN",
      "published_at": "2026-07-10T03:21:53.574905+00:00"
    },
    {
      "action_id": "dfdac5921ab657241fce58583d61bef59a369e01d2ba78191d6df6632a07fdfd#0",
      "title": "Reduce minimum Constitutional Committee size (committeeMinSize) from 7 to 5",
      "type": "ParameterChange",
      "decision": "ABSTAIN",
      "published_at": "2026-07-10T03:21:53.574905+00:00"
    },
    {
      "action_id": "c21b00f90f18fce4003edf42b0b0d455126e01c946e80cc5341a9f9750caf795#0",
      "title": "Increase Transaction and Block Memory Units (Part 1 of 2)",
      "type": "ParameterChange",
      "decision": "ABSTAIN",
      "published_at": "2026-07-10T03:21:53.574905+00:00"
    },
    {
      "action_id": "c0660dfd01b0a2d9ba7bac02014370096242ec756031b57d78080844fbbe9c05#0",
      "title": "Global Order Book connect Cardano DeFi to increase transaction",
      "type": "TreasuryWithdrawals",
      "decision": "ABSTAIN",
      "published_at": "2026-07-10T03:21:53.574905+00:00"
    },
    {
      "action_id": "8721696358acdd43e34e5ed9ef1b3e2a1d2af9c1aa1972e017b9b9271b7ddc70#0",
      "title": "Strike Finance Liquidity Deployment",
      "type": "TreasuryWithdrawals",
      "decision": "ABSTAIN",
      "published_at": "2026-07-10T03:21:53.574905+00:00"
    },
    {
      "action_id": "8ad3d454f3496a35cb0d07b0fd32f687f66338b7d60e787fc0a22939e5d8833e#12",
      "title": "Withdraw \u20b3578,571 for Gerolamo - Cardano node in typescript",
      "type": "TreasuryWithdrawals",
      "decision": "ABSTAIN",
      "published_at": "2026-07-10T03:21:53.574905+00:00"
    },
    {
      "action_id": "fff0df644d328a5367212f45bab59060bde3c4091dc96c723062896fd6197314#0",
      "title": "Rename the Chang 2 Hard Fork to the Plomin Hard Fork",
      "type": "InfoAction",
      "decision": "ABSTAIN",
      "published_at": "2026-07-10T03:21:53.574905+00:00"
    },
    {
      "action_id": "59fd353253eb177e2104e8f23ea4c63e3d32ef95c7865d03e90d3884424dc1db#0",
      "title": "Cardano\u306e\u751f\u304d\u304c\u3044 - Ikigai -",
      "type": "InfoAction",
      "decision": "ABSTAIN",
      "published_at": "2026-07-10T03:21:53.574905+00:00"
    },
    {
      "action_id": "73e171a4c0730b4b59ecae271ab89f12a9d56360b02920e1f95107dbdc1d6762#7",
      "title": "Blockfrost: Maintenance and Next Generation Indexing",
      "type": "TreasuryWithdrawals",
      "decision": "ABSTAIN",
      "published_at": "2026-07-10T03:21:53.574905+00:00"
    },
    {
      "action_id": "8ad3d454f3496a35cb0d07b0fd32f687f66338b7d60e787fc0a22939e5d8833e#36",
      "title": "Withdraw \u20b3104,347 for MLabs Research towards Tooling for Elliptical Curves...",
      "type": "TreasuryWithdrawals",
      "decision": "ABSTAIN",
      "published_at": "2026-07-10T03:21:53.574905+00:00"
    }
  ]
}
